setup.py
tests/__init__.py
tests/test_api.py
tests/test_menu.py
tests/test_message.py
tests/test_payment.py
tests/test_requestutil.py
tests/test_resource.py
wechatkit/__init__.py
wechatkit/api.py
wechatkit/basic.py
wechatkit/consts.py
wechatkit/exceptions.py
wechatkit/menu.py
wechatkit/message.py
wechatkit/payment.py
wechatkit/resource.py
wechatkit/user.py
wechatkit/utils.py
wechatkit.egg-info/PKG-INFO
wechatkit.egg-info/SOURCES.txt
wechatkit.egg-info/dependency_links.txt
wechatkit.egg-info/not-zip-safe
wechatkit.egg-info/requires.txt
wechatkit.egg-info/top_level.txt