Metadata-Version: 1.0
Name: wechatkit
Version: 0.1.0
Summary: wechatkit is a common wechat api component.
Home-page: https://github.com/istommao/wechatkit
Author: silence
Author-email: istommao@gmail.com
License: UNKNOWN
Keywords: wechatkit is a common wechat api component!
Platform: UNKNOWN
